codejournal/__init__.py
codejournal/apply_func.py
codejournal/config.py
codejournal/data.py
codejournal/hacks.py
codejournal/imports.py
codejournal/loggers.py
codejournal/modeling.py
codejournal/slack.py
codejournal/trainer.py
codejournal/utils.py
codejournal-0.2.0.1.dist-info/LICENSE
codejournal-0.2.0.1.dist-info/METADATA
codejournal-0.2.0.1.dist-info/WHEEL
codejournal-0.2.0.1.dist-info/top_level.txt
codejournal-0.2.0.1.dist-info/RECORD
