Metadata-Version: 2.1
Name: codejournal
Version: 0.2.0.1
Summary: A Python package hackable code snips package for faster pytorch-AI development
Home-page: https://github.com/yourusername/codejournal
Author: Siva Sankar S
Author-email: sysrunai@gmail.com
Classifier: Programming Language :: Python :: 3
Classifier: License :: OSI Approved :: MIT License
Classifier: Operating System :: OS Independent
Requires-Python: >=3.9
License-File: LICENSE
Requires-Dist: joblib
Requires-Dist: matplotlib
Requires-Dist: moviepy
Requires-Dist: numpy
Requires-Dist: pandas
Requires-Dist: pycryptodome
Requires-Dist: python-dotenv
Requires-Dist: Requests
Requires-Dist: safetensors
Requires-Dist: seaborn
Requires-Dist: torch
Requires-Dist: torchvision
Requires-Dist: tqdm
Requires-Dist: wandb
Requires-Dist: opencv-python
Requires-Dist: huggingface-hub
Requires-Dist: randomname
